<options>
  <configurable id="preferences.keymap" configurable_name="按键映射">
    <option name="bean" path="ActionManager" hit="CDI Bean 描述符(beans.xml)" />
    <option name="beans" path="ActionManager" hit="CDI Bean 描述符(beans.xml)" />
    <option name="cdi" path="ActionManager" hit="CDI Bean 描述符(beans.xml)" />
    <option name="xml" path="ActionManager" hit="CDI Bean 描述符(beans.xml)" />
    <option name="描述符" path="ActionManager" hit="CDI Bean 描述符(beans.xml)" />
    <option name="beans" path="ActionManager" hit="创建 beans.xml 配置文件" />
    <option name="xml" path="ActionManager" hit="创建 beans.xml 配置文件" />
    <option name="创建" path="ActionManager" hit="创建 beans.xml 配置文件" />
    <option name="配置文件" path="ActionManager" hit="创建 beans.xml 配置文件" />
  </configurable>
</options>