<options>
  <configurable id="preferences.keymap" configurable_name="按键映射">
    <option name="" path="ActionManager" hit="" />
    <option name="copy" path="ActionManager" hit="Copy" />
    <option name="column" path="ActionManager" hit="Select Column" />
    <option name="select" path="ActionManager" hit="Select Column" />
    <option name="上一页" path="ActionManager" hit="上一页" />
    <option name="下一页" path="ActionManager" hit="下一页" />
    <option name="值编辑器" path="ActionManager" hit="值编辑器" />
    <option name="值编辑器和聚合视图" path="ActionManager" hit="值编辑器和聚合视图" />
    <option name="克隆列" path="ActionManager" hit="克隆列" />
    <option name="克隆行" path="ActionManager" hit="克隆行" />
    <option name="分页" path="ActionManager" hit="分页" />
    <option name="切换格式" path="ActionManager" hit="切换格式" />
    <option name="切换自动换行" path="ActionManager" hit="切换自动换行" />
    <option name="列列表" path="ActionManager" hit="列列表" />
    <option name="删除所选列" path="ActionManager" hit="删除所选列" />
    <option name="删除所选行" path="ActionManager" hit="删除所选行" />
    <option name="加载文件" path="ActionManager" hit="加载文件…" />
    <option name="升序" path="ActionManager" hit="升序" />
    <option name="取消选择上一个匹配项" path="ActionManager" hit="取消选择上一个匹配项" />
    <option name="启用所有聚合器" path="ActionManager" hit="启用所有聚合器" />
    <option name="在当前页面上查找" path="ActionManager" hit="在当前页面上查找" />
    <option name="复制列名称" path="ActionManager" hit="复制列名称" />
    <option name="复制聚合结果" path="ActionManager" hit="复制聚合结果" />
    <option name="导出数据" path="ActionManager" hit="导出数据…" />
    <option name="将所有数据导出到文件或剪贴板" path="ActionManager" hit="将所有数据导出到文件或剪贴板" />
    <option name="展开所选列" path="ActionManager" hit="展开所选列" />
    <option name="常规" path="ActionManager" hit="常规" />
    <option name="打开数据视图外观设置" path="ActionManager" hit="打开数据视图外观设置…" />
    <option name="扩大选区" path="ActionManager" hit="扩大选区" />
    <option name="排序" path="ActionManager" hit="排序" />
    <option name="提取程序" path="ActionManager" hit="提取程序" />
    <option name="收缩选区" path="ActionManager" hit="收缩选区" />
    <option name="文本" path="ActionManager" hit="文本" />
    <option name="显示" path="ActionManager" hit="显示/隐藏列" />
    <option name="隐藏列" path="ActionManager" hit="显示/隐藏列" />
    <option name="显示值编辑器" path="ActionManager" hit="显示值编辑器" />
    <option name="显示图表" path="ActionManager" hit="显示图表" />
    <option name="显示所有列" path="ActionManager" hit="显示所有列" />
    <option name="显示所选单元的值之间的不同" path="ActionManager" hit="显示所选单元的值之间的不同" />
    <option name="显示筛选器" path="ActionManager" hit="显示筛选器" />
    <option name="显示聚合视图" path="ActionManager" hit="显示聚合视图" />
    <option name="更改显示类型" path="ActionManager" hit="更改显示类型" />
    <option name="更改编码" path="ActionManager" hit="更改编码…" />
    <option name="更改页面大小" path="ActionManager" hit="更改页面大小" />
    <option name="最后一页" path="ActionManager" hit="最后一页" />
    <option name="查看方式" path="ActionManager" hit="查看方式" />
    <option name="查询结果" path="ActionManager" hit="查询结果" />
    <option name="树" path="ActionManager" hit="树" />
    <option name="比较单元" path="ActionManager" hit="比较单元…" />
    <option name="添加列" path="ActionManager" hit="添加列" />
    <option name="添加升序" path="ActionManager" hit="添加升序" />
    <option name="添加行" path="ActionManager" hit="添加行" />
    <option name="添加降序" path="ActionManager" hit="添加降序" />
    <option name="清除排序" path="ActionManager" hit="清除排序" />
    <option name="禁用所有聚合器" path="ActionManager" hit="禁用所有聚合器" />
    <option name="移至右侧" path="ActionManager" hit="移至右侧" />
    <option name="移至底部" path="ActionManager" hit="移至底部" />
    <option name="第一行为标头" path="ActionManager" hit="第一行为标头" />
    <option name="第一页" path="ActionManager" hit="第一页" />
    <option name="粘贴格式" path="ActionManager" hit="粘贴格式" />
    <option name="结果" path="ActionManager" hit="结果" />
    <option name="结果标题" path="ActionManager" hit="结果标题" />
    <option name="编辑" path="ActionManager" hit="编辑" />
    <option name="编辑所选单元" path="ActionManager" hit="编辑所选单元" />
    <option name="缩小所选列的范围" path="ActionManager" hit="缩小所选列的范围" />
    <option name="聚合视图" path="ActionManager" hit="聚合视图" />
    <option name="行" path="ActionManager" hit="行…" />
    <option name="行计数" path="ActionManager" hit="行计数" />
    <option name="表" path="ActionManager" hit="表" />
    <option name="设置高亮显示语言" path="ActionManager" hit="设置高亮显示语言…" />
    <option name="转到脚本目录" path="ActionManager" hit="转到脚本目录" />
    <option name="转置" path="ActionManager" hit="转置" />
    <option name="还原所选更改" path="ActionManager" hit="还原所选更改" />
    <option name="还原所选条目" path="ActionManager" hit="还原所选条目" />
    <option name="选择下一个匹配项" path="ActionManager" hit="选择下一个匹配项" />
    <option name="选择所有匹配项" path="ActionManager" hit="选择所有匹配项" />
    <option name="选择数据提取程序" path="ActionManager" hit="选择数据提取程序" />
    <option name="csv" path="ActionManager" hit="配置 CSV 格式…" />
    <option name="格式" path="ActionManager" hit="配置 CSV 格式…" />
    <option name="配置" path="ActionManager" hit="配置 CSV 格式…" />
    <option name="重命名" path="ActionManager" hit="重命名…" />
    <option name="重新加载页面" path="ActionManager" hit="重新加载页面" />
    <option name="重置列宽" path="ActionManager" hit="重置列宽" />
    <option name="重置视图" path="ActionManager" hit="重置视图" />
    <option name="降序" path="ActionManager" hit="降序" />
    <option name="隐藏值编辑器" path="ActionManager" hit="隐藏值编辑器" />
    <option name="隐藏其他列" path="ActionManager" hit="隐藏其他列" />
    <option name="隐藏列" path="ActionManager" hit="隐藏列" />
  </configurable>
  <configurable id="reference.settingsdialog.IDE.editor.colors.数据编辑器和查看器" configurable_name="数据编辑器和查看器">
    <option name="数据编辑器和查看器" hit="数据编辑器和查看器" />
    <option name="null" hit="数据网格//Null 数据" />
    <option name="数据" hit="数据网格//Null 数据" />
    <option name="数据网格" hit="数据网格//Null 数据" />
    <option name="交替行颜色" hit="数据网格//交替行颜色" />
    <option name="数据网格" hit="数据网格//交替行颜色" />
    <option name="图像数据" hit="数据网格//图像数据" />
    <option name="数据网格" hit="数据网格//图像数据" />
    <option name="数据网格" hit="数据网格//错误数据" />
    <option name="错误数据" hit="数据网格//错误数据" />
  </configurable>
  <configurable id="database.data.csv.formats" configurable_name="CSV 格式">
    <option name="" hit=" N" />
    <option name="n" hit=" N" />
    <option name="csv" hit="CSV 格式" />
    <option name="格式" hit="CSV 格式" />
    <option name="n" hit="null 值文本 N  " />
    <option name="null" hit="null 值文本 N  " />
    <option name="值文本" hit="null 值文本 N  " />
    <option name="q" hit="为值加引号 Q  " />
    <option name="为值加引号" hit="为值加引号 Q  " />
    <option name="从不" hit="从不" />
    <option name="s" hit="值分隔符 S  " />
    <option name="值分隔符" hit="值分隔符 S  " />
    <option name="分号" hit="分号" />
    <option name="制表符" hit="制表符" />
    <option name="头格式" hit="头格式" />
    <option name="始终" hit="始终" />
    <option name="引用" hit="引用 " />
    <option name="换行符" hit="换行符" />
    <option name="未定义" hit="未定义" />
    <option name="格式" hit="格式 " />
    <option name="后缀" hit="添加行前缀 后缀" />
    <option name="添加行前缀" hit="添加行前缀 后缀" />
    <option name="w" hit="清除空格 W " />
    <option name="清除空格" hit="清除空格 W " />
    <option name="空字符串" hit="空字符串" />
    <option name="空格" hit="空格" />
    <option name="h" hit="第一列是头 H " />
    <option name="第一列是头" hit="第一列是头 H " />
    <option name="h" hit="第一行是头 H " />
    <option name="第一行是头" hit="第一行是头 H " />
    <option name="管道" hit="管道" />
    <option name="r" hit="行分隔符 R  " />
    <option name="行分隔符" hit="行分隔符 R  " />
    <option name="x" hit="行前缀 X  " />
    <option name="行前缀" hit="行前缀 X  " />
    <option name="i" hit="行后缀 I  " />
    <option name="行后缀" hit="行后缀 I  " />
    <option name="逗号" hit="逗号" />
    <option name="需要时" hit="需要时" />
  </configurable>
  <configurable id="database.data.views.appearance" configurable_name="数据编辑器和查看器">
    <option name="交替行颜色" hit="交替行颜色" />
    <option name="使用自定义字体" hit="使用自定义字体 " />
    <option name="复选框" hit="复选框" />
    <option name="大小" hit="大小 " />
    <option name="将布尔值显示为" hit="将布尔值显示为 " />
    <option name="数据编辑器和查看器" hit="数据编辑器和查看器" />
    <option name="文本" hit="文本" />
    <option name="行高" hit="行高 " />
  </configurable>
</options>