<options>
  <configurable id="preferences.keymap" configurable_name="键盘映射">
    <option name="" path="ActionManager" hit="" />
    <option name="cte" path="ActionManager" hit="子查询为 CTE" />
    <option name="子查询为" path="ActionManager" hit="子查询为 CTE" />
    <option name="提取例程" path="ActionManager" hit="提取例程…" />
    <option name="sql" path="ActionManager" hit="更改 SQL 方言" />
    <option name="方言" path="ActionManager" hit="更改 SQL 方言" />
    <option name="更改" path="ActionManager" hit="更改 SQL 方言" />
    <option name="表别名" path="ActionManager" hit="表别名…" />
    <option name="选择当前语句" path="ActionManager" hit="选择当前语句" />
  </configurable>
  <configurable id="editor.breadcrumbs" configurable_name="路径导航">
    <option name="sql" hit="SQL" />
  </configurable>
</options>