<options>
  <configurable id="rsyncConfigurable" configurable_name="Rsync">
    <option name="" hit=" Rsync 选项列表" />
    <option name="rsync" hit=" Rsync 选项列表" />
    <option name="选项列表" hit=" Rsync 选项列表" />
    <option name="" hit=" 通过 SSH 连接时 Rsync 将使用此可执行文件" />
    <option name="rsync" hit=" 通过 SSH 连接时 Rsync 将使用此可执行文件" />
    <option name="ssh" hit=" 通过 SSH 连接时 Rsync 将使用此可执行文件" />
    <option name="将使用此可执行文件" hit=" 通过 SSH 连接时 Rsync 将使用此可执行文件" />
    <option name="连接时" hit=" 通过 SSH 连接时 Rsync 将使用此可执行文件" />
    <option name="通过" hit=" 通过 SSH 连接时 Rsync 将使用此可执行文件" />
    <option name="rsync" hit="Rsync" />
    <option name="rsync" hit="Rsync 可执行文件路径 " />
    <option name="可执行文件路径" hit="Rsync 可执行文件路径 " />
    <option name="rsync" hit="Rsync 选项 " />
    <option name="选项" hit="Rsync 选项 " />
    <option name="shell" hit="Shell 可执行文件路径 " />
    <option name="可执行文件路径" hit="Shell 可执行文件路径 " />
    <option name="恢复默认值" hit="恢复默认值" />
    <option name="测试连接" hit="测试连接" />
  </configurable>
</options>