<options>
  <configurable id="preferences.keymap" configurable_name="键盘映射">
    <option name="" path="ActionManager" hit="" />
    <option name="settings" path="ActionManager" hit="Settings Sync" />
    <option name="sync" path="ActionManager" hit="Settings Sync" />
    <option name="history" path="ActionManager" hit="Settings Sync History" />
    <option name="settings" path="ActionManager" hit="Settings Sync History" />
    <option name="sync" path="ActionManager" hit="Settings Sync History" />
    <option name="settings" path="ActionManager" hit="Settings Sync Troubleshooting" />
    <option name="sync" path="ActionManager" hit="Settings Sync Troubleshooting" />
    <option name="troubleshooting" path="ActionManager" hit="Settings Sync Troubleshooting" />
    <option name="同步设置" path="ActionManager" hit="同步设置" />
  </configurable>
</options>