<options>
  <configurable id="preferences.keymap" configurable_name="键盘映射">
    <option name="" path="ActionManager" hit="" />
    <option name="for" path="ActionManager" hit="For 循环" />
    <option name="循环" path="ActionManager" hit="For 循环" />
    <option name="until" path="ActionManager" hit="Until 循环" />
    <option name="循环" path="ActionManager" hit="Until 循环" />
    <option name="while" path="ActionManager" hit="While 循环" />
    <option name="循环" path="ActionManager" hit="While 循环" />
    <option name="for" path="ActionManager" hit="创建 for 循环" />
    <option name="创建" path="ActionManager" hit="创建 for 循环" />
    <option name="循环" path="ActionManager" hit="创建 for 循环" />
    <option name="until" path="ActionManager" hit="创建 until 循环" />
    <option name="创建" path="ActionManager" hit="创建 until 循环" />
    <option name="循环" path="ActionManager" hit="创建 until 循环" />
    <option name="while" path="ActionManager" hit="创建 while 循环" />
    <option name="创建" path="ActionManager" hit="创建 while 循环" />
    <option name="循环" path="ActionManager" hit="创建 while 循环" />
    <option name="运行文件" path="ActionManager" hit="运行文件" />
    <option name="shell" path="ActionManager" hit="运行终端当前的 shell 文件" />
    <option name="文件" path="ActionManager" hit="运行终端当前的 shell 文件" />
    <option name="运行终端当前的" path="ActionManager" hit="运行终端当前的 shell 文件" />
  </configurable>
  <configurable id="reference.settingsdialog.IDE.editor.colors.Shell Script" configurable_name="Shell Script">
    <option name="script" hit="Shell Script" />
    <option name="shell" hit="Shell Script" />
    <option name="here" hit="Here 文档" />
    <option name="文档" hit="Here 文档" />
    <option name="here" hit="Here 文档开始" />
    <option name="文档开始" hit="Here 文档开始" />
    <option name="here" hit="Here 文档结束" />
    <option name="文档结束" hit="Here 文档结束" />
    <option name="shebang" hit="Shebang 注释" />
    <option name="注释" hit="Shebang 注释" />
    <option name="关键字" hit="关键字" />
    <option name="函数声明" hit="函数声明" />
    <option name="原始字符串" hit="原始字符串" />
    <option name="反引号" hit="反引号" />
    <option name="变量" hit="变量//变量声明" />
    <option name="变量声明" hit="变量//变量声明" />
    <option name="变量" hit="变量//变量用法" />
    <option name="变量用法" hit="变量//变量用法" />
    <option name="变量" hit="变量//组合变量" />
    <option name="组合变量" hit="变量//组合变量" />
    <option name="subshell" hit="命令//subshell 命令" />
    <option name="命令" hit="命令//subshell 命令" />
    <option name="命令" hit="命令//泛型命令" />
    <option name="泛型命令" hit="命令//泛型命令" />
    <option name="圆括号" hit="大括号//圆括号" />
    <option name="大括号" hit="大括号//圆括号" />
    <option name="大括号" hit="大括号//大括号" />
    <option name="大括号" hit="大括号//方括号" />
    <option name="方括号" hit="大括号//方括号" />
    <option name="字符串" hit="字符串" />
    <option name="数字" hit="数字" />
    <option name="条件运算符" hit="条件运算符" />
    <option name="行注释" hit="行注释" />
    <option name="重定向" hit="重定向" />
  </configurable>
</options>