<options>
  <configurable id="preferences.keymap" configurable_name="键盘映射">
    <option name="" path="ActionManager" hit="" />
    <option name="detection" path="ActionManager" hit="Enable Migrations Detection" />
    <option name="enable" path="ActionManager" hit="Enable Migrations Detection" />
    <option name="migrations" path="ActionManager" hit="Enable Migrations Detection" />
    <option name="kotlin" path="ActionManager" hit="Kotlin" />
    <option name="beta" path="ActionManager" hit="Kotlin Script (Beta)" />
    <option name="kotlin" path="ActionManager" hit="Kotlin Script (Beta)" />
    <option name="script" path="ActionManager" hit="Kotlin Script (Beta)" />
    <option name="beta" path="ActionManager" hit="Kotlin Worksheet (Beta)" />
    <option name="kotlin" path="ActionManager" hit="Kotlin Worksheet (Beta)" />
    <option name="worksheet" path="ActionManager" hit="Kotlin Worksheet (Beta)" />
    <option name="kotlin" path="ActionManager" hit="Kotlin 类/文件" />
    <option name="文件" path="ActionManager" hit="Kotlin 类/文件" />
    <option name="类" path="ActionManager" hit="Kotlin 类/文件" />
    <option name="kotlin" path="ActionManager" hit="Kotlin 重构测试" />
    <option name="重构测试" path="ActionManager" hit="Kotlin 重构测试" />
    <option name="setup" path="ActionManager" hit="SetUp 函数" />
    <option name="函数" path="ActionManager" hit="SetUp 函数" />
    <option name="teardown" path="ActionManager" hit="TearDown 函数" />
    <option name="函数" path="ActionManager" hit="TearDown 函数" />
    <option name="equals" path="ActionManager" hit="equals() 和 hashCode()" />
    <option name="hashcode" path="ActionManager" hit="equals() 和 hashCode()" />
    <option name="和" path="ActionManager" hit="equals() 和 hashCode()" />
    <option name="tostring" path="ActionManager" hit="toString()" />
    <option name="kotlin" path="ActionManager" hit="为 Kotlin 插件配置自动更新" />
    <option name="为" path="ActionManager" hit="为 Kotlin 插件配置自动更新" />
    <option name="插件配置自动更新" path="ActionManager" hit="为 Kotlin 插件配置自动更新" />
    <option name="函数" path="ActionManager" hit="函数…" />
    <option name="函数到作用域" path="ActionManager" hit="函数到作用域…" />
    <option name="kotlin" path="ActionManager" hit="创建新的 Kotlin 工作表" />
    <option name="创建新的" path="ActionManager" hit="创建新的 Kotlin 工作表" />
    <option name="工作表" path="ActionManager" hit="创建新的 Kotlin 工作表" />
    <option name="kotlin" path="ActionManager" hit="创建新的 Kotlin 类或文件" />
    <option name="创建新的" path="ActionManager" hit="创建新的 Kotlin 类或文件" />
    <option name="类或文件" path="ActionManager" hit="创建新的 Kotlin 类或文件" />
    <option name="kotlin" path="ActionManager" hit="创建新的 Kotlin 脚本" />
    <option name="创建新的" path="ActionManager" hit="创建新的 Kotlin 脚本" />
    <option name="脚本" path="ActionManager" hit="创建新的 Kotlin 脚本" />
    <option name="在打开的项目上测试移动重构" path="ActionManager" hit="在打开的项目上测试移动重构" />
    <option name="java" path="ActionManager" hit="将 Java 文件转换为 Kotlin 文件" />
    <option name="kotlin" path="ActionManager" hit="将 Java 文件转换为 Kotlin 文件" />
    <option name="将" path="ActionManager" hit="将 Java 文件转换为 Kotlin 文件" />
    <option name="文件" path="ActionManager" hit="将 Java 文件转换为 Kotlin 文件" />
    <option name="文件转换为" path="ActionManager" hit="将 Java 文件转换为 Kotlin 文件" />
    <option name="kotlin" path="ActionManager" hit="将 Kotlin 项目概览复制到剪贴板" />
    <option name="将" path="ActionManager" hit="将 Kotlin 项目概览复制到剪贴板" />
    <option name="项目概览复制到剪贴板" path="ActionManager" hit="将 Kotlin 项目概览复制到剪贴板" />
    <option name="属性" path="ActionManager" hit="属性…" />
    <option name="形参函数" path="ActionManager" hit="形参函数" />
    <option name="测试函数" path="ActionManager" hit="测试函数" />
    <option name="类型别名" path="ActionManager" hit="类型别名…" />
    <option name="类型形参" path="ActionManager" hit="类型形参…" />
    <option name="辅助构造函数" path="ActionManager" hit="辅助构造函数" />
    <option name="运行代码迁移" path="ActionManager" hit="运行代码迁移" />
    <option name="kotlin" path="ActionManager" hit="配置 Kotlin 插件更新" />
    <option name="插件更新" path="ActionManager" hit="配置 Kotlin 插件更新" />
    <option name="配置" path="ActionManager" hit="配置 Kotlin 插件更新" />
  </configurable>
  <configurable id="editor.breadcrumbs" configurable_name="路径导航">
    <option name="kotlin" hit="Kotlin" />
  </configurable>
  <configurable id="reference.settingsdialog.IDE.editor.colors.Kotlin" configurable_name="Kotlin">
    <option name="kotlin" hit="Kotlin" />
    <option name="dsl" hit="Dsl//样式1" />
    <option name="样式" hit="Dsl//样式1" />
    <option name="dsl" hit="Dsl//样式2" />
    <option name="样式" hit="Dsl//样式2" />
    <option name="dsl" hit="Dsl//样式3" />
    <option name="样式" hit="Dsl//样式3" />
    <option name="dsl" hit="Dsl//样式4" />
    <option name="样式" hit="Dsl//样式4" />
    <option name="val" hit="关键字//'val'" />
    <option name="关键字" hit="关键字//'val'" />
    <option name="var" hit="关键字//'var'" />
    <option name="关键字" hit="关键字//'var'" />
    <option name="修饰符" hit="关键字//修饰符" />
    <option name="关键字" hit="关键字//修饰符" />
    <option name="关键字" hit="关键字//关键字" />
    <option name="函数" hit="函数//函数声明" />
    <option name="函数声明" hit="函数//函数声明" />
    <option name="函数" hit="函数//函数调用" />
    <option name="函数调用" hit="函数//函数调用" />
    <option name="函数" hit="函数//动态函数调用" />
    <option name="动态函数调用" hit="函数//动态函数调用" />
    <option name="函数" hit="函数//扩展函数调用" />
    <option name="扩展函数调用" hit="函数//扩展函数调用" />
    <option name="函数" hit="函数//挂起函数调用" />
    <option name="挂起函数调用" hit="函数//挂起函数调用" />
    <option name="函数" hit="函数//构造函数调用" />
    <option name="构造函数调用" hit="函数//构造函数调用" />
    <option name="函数" hit="函数//软件包级函数调用" />
    <option name="软件包级函数调用" hit="函数//软件包级函数调用" />
    <option name="参数" hit="参数//参数" />
    <option name="命名实参" hit="命名实参" />
    <option name="中括号" hit="大括号和运算符//中括号" />
    <option name="大括号和运算符" hit="大括号和运算符//中括号" />
    <option name="冒号" hit="大括号和运算符//冒号" />
    <option name="大括号和运算符" hit="大括号和运算符//冒号" />
    <option name="分号" hit="大括号和运算符//分号" />
    <option name="大括号和运算符" hit="大括号和运算符//分号" />
    <option name="圆括号" hit="大括号和运算符//圆括号" />
    <option name="大括号和运算符" hit="大括号和运算符//圆括号" />
    <option name="大括号" hit="大括号和运算符//大括号" />
    <option name="大括号和运算符" hit="大括号和运算符//大括号" />
    <option name="大括号和运算符" hit="大括号和运算符//点" />
    <option name="点" hit="大括号和运算符//点" />
    <option name="大括号和运算符" hit="大括号和运算符//运算符符号" />
    <option name="运算符符号" hit="大括号和运算符//运算符符号" />
    <option name="大括号和运算符" hit="大括号和运算符//逗号" />
    <option name="逗号" hit="大括号和运算符//逗号" />
    <option name="字符串" hit="字符串//字符串和模板大括号中的转义" />
    <option name="字符串和模板大括号中的转义" hit="字符串//字符串和模板大括号中的转义" />
    <option name="字符串" hit="字符串//字符串文本" />
    <option name="字符串文本" hit="字符串//字符串文本" />
    <option name="字符串" hit="字符串//转义序列//无效" />
    <option name="无效" hit="字符串//转义序列//无效" />
    <option name="转义序列" hit="字符串//转义序列//无效" />
    <option name="android" hit="属性和变量//Android 扩展合成属性" />
    <option name="属性和变量" hit="属性和变量//Android 扩展合成属性" />
    <option name="扩展合成属性" hit="属性和变量//Android 扩展合成属性" />
    <option name="var" hit="属性和变量//Var (可变变量、形参或属性)" />
    <option name="可变变量" hit="属性和变量//Var (可变变量、形参或属性)" />
    <option name="属性和变量" hit="属性和变量//Var (可变变量、形参或属性)" />
    <option name="形参或属性" hit="属性和变量//Var (可变变量、形参或属性)" />
    <option name="动态属性" hit="属性和变量//动态属性" />
    <option name="属性和变量" hit="属性和变量//动态属性" />
    <option name="包含自定义属性声明的实例属性" hit="属性和变量//包含自定义属性声明的实例属性" />
    <option name="属性和变量" hit="属性和变量//包含自定义属性声明的实例属性" />
    <option name="包含自定义属性声明的软件包级属性" hit="属性和变量//包含自定义属性声明的软件包级属性" />
    <option name="属性和变量" hit="属性和变量//包含自定义属性声明的软件包级属性" />
    <option name="变量作为函数调用" hit="属性和变量//变量作为函数调用" />
    <option name="属性和变量" hit="属性和变量//变量作为函数调用" />
    <option name="变量作为类似函数的调用" hit="属性和变量//变量作为类似函数的调用" />
    <option name="属性和变量" hit="属性和变量//变量作为类似函数的调用" />
    <option name="合成扩展属性" hit="属性和变量//合成扩展属性" />
    <option name="属性和变量" hit="属性和变量//合成扩展属性" />
    <option name="实例属性" hit="属性和变量//实例属性" />
    <option name="属性和变量" hit="属性和变量//实例属性" />
    <option name="局部变量或值" hit="属性和变量//局部变量或值" />
    <option name="属性和变量" hit="属性和变量//局部变量或值" />
    <option name="属性和变量" hit="属性和变量//扩展属性" />
    <option name="扩展属性" hit="属性和变量//扩展属性" />
    <option name="属性和变量" hit="属性和变量//支持字段变量" />
    <option name="支持字段变量" hit="属性和变量//支持字段变量" />
    <option name="属性和变量" hit="属性和变量//软件包级属性" />
    <option name="软件包级属性" hit="属性和变量//软件包级属性" />
    <option name="属性和变量" hit="属性和变量//闭包中捕获的变量和值" />
    <option name="闭包中捕获的变量和值" hit="属性和变量//闭包中捕获的变量和值" />
    <option name="lambda" hit="形参//lambda 表达式默认形参" />
    <option name="形参" hit="形参//lambda 表达式默认形参" />
    <option name="表达式默认形参" hit="形参//lambda 表达式默认形参" />
    <option name="形参" hit="形参//类型形参" />
    <option name="类型形参" hit="形参//类型形参" />
    <option name="lambda" hit="括号和运算符//lambda 表达式大括号和箭头" />
    <option name="括号和运算符" hit="括号和运算符//lambda 表达式大括号和箭头" />
    <option name="表达式大括号和箭头" hit="括号和运算符//lambda 表达式大括号和箭头" />
    <option name="双重冒号" hit="括号和运算符//双重冒号" />
    <option name="括号和运算符" hit="括号和运算符//双重冒号" />
    <option name="null" hit="括号和运算符//可 null 性类型标记" />
    <option name="可" hit="括号和运算符//可 null 性类型标记" />
    <option name="性类型标记" hit="括号和运算符//可 null 性类型标记" />
    <option name="括号和运算符" hit="括号和运算符//可 null 性类型标记" />
    <option name="安全访问的点" hit="括号和运算符//安全访问的点" />
    <option name="括号和运算符" hit="括号和运算符//安全访问的点" />
    <option name="括号和运算符" hit="括号和运算符//箭头" />
    <option name="箭头" hit="括号和运算符//箭头" />
    <option name="null" hit="括号和运算符//非 null 断言" />
    <option name="括号和运算符" hit="括号和运算符//非 null 断言" />
    <option name="断言" hit="括号和运算符//非 null 断言" />
    <option name="非" hit="括号和运算符//非 null 断言" />
    <option name="数字" hit="数字" />
    <option name="智能常量" hit="智能转换//智能常量" />
    <option name="智能转换" hit="智能转换//智能常量" />
    <option name="智能转换" hit="智能转换//智能转换值" />
    <option name="智能转换值" hit="智能转换//智能转换值" />
    <option name="智能转换" hit="智能转换//智能转换隐式接收器" />
    <option name="智能转换隐式接收器" hit="智能转换//智能转换隐式接收器" />
    <option name="标签" hit="标签" />
    <option name="注解" hit="注解//注解名称" />
    <option name="注解名称" hit="注解//注解名称" />
    <option name="注解" hit="注解//注解特性名称" />
    <option name="注解特性名称" hit="注解//注解特性名称" />
    <option name="kdoc" hit="注释//KDoc//KDoc 标记" />
    <option name="标记" hit="注释//KDoc//KDoc 标记" />
    <option name="注释" hit="注释//KDoc//KDoc 标记" />
    <option name="kdoc" hit="注释//KDoc//KDoc 标记中的链接" />
    <option name="标记中的链接" hit="注释//KDoc//KDoc 标记中的链接" />
    <option name="注释" hit="注释//KDoc//KDoc 标记中的链接" />
    <option name="kdoc" hit="注释//KDoc//KDoc 注释" />
    <option name="注释" hit="注释//KDoc//KDoc 注释" />
    <option name="块注释" hit="注释//块注释" />
    <option name="注释" hit="注释//块注释" />
    <option name="注释" hit="注释//行注释" />
    <option name="行注释" hit="注释//行注释" />
    <option name="对象" hit="类和接口//对象" />
    <option name="类和接口" hit="类和接口//对象" />
    <option name="抽象类" hit="类和接口//抽象类" />
    <option name="类和接口" hit="类和接口//抽象类" />
    <option name="接口" hit="类和接口//接口" />
    <option name="类和接口" hit="类和接口//接口" />
    <option name="枚举" hit="类和接口//枚举" />
    <option name="类和接口" hit="类和接口//枚举" />
    <option name="枚举条目" hit="类和接口//枚举条目" />
    <option name="类和接口" hit="类和接口//枚举条目" />
    <option name="类" hit="类和接口//类" />
    <option name="类和接口" hit="类和接口//类" />
    <option name="类和接口" hit="类和接口//类型别名" />
    <option name="类型别名" hit="类和接口//类型别名" />
    <option name="语义高亮显示" hit="语义高亮显示" />
  </configurable>
</options>